{
	"pages": [
		{
			"path": "pages/play/renji",
			"style": {}
		},
		{
			"path": "pages/play/renjigame",
			"style": {}
		},
		{
			"path": "pages/viewgame/gamerecords",
			"style": {}
		},
		{
			"path": "pages/tiku/tiku",
			"style": {}
		},
		{
			"path": "pages/topic/topic",
			"style": {}
		}
	],
	
	"sitemapLocation": "sitemap.json",
	"deviceOrientation": "portrait",
	"globalStyle": {
		"navigationStyle":"custom",
		"backgroundColor": "#eabe79",
		"backgroundTextStyle": "light",
		"navigationBarBackgroundColor": "#3c3c3c",
		"navigationBarTitleText": "",
		"navigationBarTextStyle": "white"
	},
	"subPackages": []
}